Workbook

Sheet M.C.5.1
A1: Mini-case 5.1
A2: Assumptions | E2: TASK A | H2: TASK B | M2: TASK C
A3: Probabilities | B3: 0.5 | C3: 0.5 | E3: CE[V0(Firm)] | F3: {=SUM(B4:C4*B3:C3)} -> 215 | I3: T = 0 | J3: T = 1 | M3: The manager will raise debt. She won't abandon the investment because it will increase E in comparison to no-investment E. Since the information about present state of company is uncertain, it is clear that external investors do not have the full information in their possesion. Thus, manager has reasons to consider the pecking order. Debt is risk-free and hence is not affected by information assymetry.
A4: V0(Firm) | B4: 290 | C4: 140 | E4: Vpost-investment(Firm) | F4: =F3+C7 -> 269 | J4: Up-state | K4: Down-state
E5: Share to offer | F5: =C6/F4 -> 0.15613383 | H5: V(Firm) | I5: {=SUM(J5:K5*B3:C3)} -> 269 | J5: =B4+$C$7 -> 344 | K5: =C4+$C$7 -> 194
A6: New project | B6: Inv. cost | C6: 42 | E6: V(Eold) | F6: =F4*(1-F5) -> 227 | H6: D | I6: {=SUM(J6:K6*B3:C3)} -> 42 | J6: =IF(J5<$C$6,J5,$C$6) -> 42 | K6: =IF(K5<$C$6,K5,$C$6) -> 42
B7: CF | C7: 54 | H7: E | I7: =I5-I6 -> 227 | J7: =J5-J6 -> 302 | K7: =K5-K6 -> 152
A9: FDsenior | B9: 170
A11: TASK D | F11: TASK E
B12: T = 0 | C12: T = 1 | G12: T = 0 | H12: T = 1
C13: Up-State | D13: Down-state | H13: Up-State | I13: Down-state
A14: V(Firm) | B14: {=SUM(C14:D14*B3:C3)} -> 215 | C14: =B4 -> 290 | D14: =C4 -> 140 | F14: V(Firm) | G14: {=SUM(H14:I14*B3:C3)} -> 269 | H14: =C14+C7 -> 344 | I14: =D14+C7 -> 194 | K14: TASK F
A15: Dsenior | B15: {=SUM(C15:D15*B3:C3)} -> 155 | C15: =IF(C14-$B$9<0,C14,$B$9) -> 170 | D15: =IF(D14-$B$9<0,D14,$B$9) -> 140 | F15: Dsenior | G15: {=SUM(H15:I15*B3:C3)} -> 170 | H15: =IF(H14-$B$9<0,H14,$B$9) -> 170 | I15: =IF(I14-$B$9<0,I14,$B$9) -> 170 | K15: Here it's crusial to observe that Eold falls in case of investment given additional debt in the capital structure. Thus, the management doesn't implement the project. We observe the case of debt overhang in the company
A16: E | B16: =B14-B15 -> 60 | C16: =C14-C15 -> 120 | D16: =D14-D15 -> 0 | F16: Djunior | G16: 42 | H16: =(G16-I16*C3)/B3 -> 60 | I16: =I14-I15 -> 24
F17: E | G17: =G14-G15-G16 -> 57 | H17: =H14-H15-H16 -> 114 | I17: =I14-I15-I16 -> 0
A18: Vpost-investment(Firm) | D18: =B14+C7 -> 269
A19: Vpost-investment(E) | D19: =D18-B9 -> 99
A20: Share of equity to offer to new investors | D20: =C6/D19 -> 0.42424242
A21: V(Eold) | D21: =D19*(1-D20) -> 57

Sheet M.C.5.2
A1: Mini-case 5.2
A2: Government policies | D2: TASK A
A3: Direct subsidy | B3: 12 | E3: T = 0 | F3: T = 1
A4: Credit guarantee | B4: Newly issued junior debt | F4: Up-State | G4: Down-state
D5: V(Firm) | E5: {=SUM(F5:G5*'M.C.5.1'!$B$3:$C$3)} -> 269 | F5: ='M.C.5.1'!B4+'M.C.5.1'!$C$7 -> 344 | G5: ='M.C.5.1'!C4+'M.C.5.1'!$C$7 -> 194
D6: Dsenior | E6: {=SUM(F6:G6*'M.C.5.1'!$B$3:$C$3)} -> 170 | F6: =IF(F5-'M.C.5.1'!$B$9<0,'M.C.5.2'!F5,'M.C.5.1'!$B$9) -> 170 | G6: =IF(G5-'M.C.5.1'!$B$9<0,'M.C.5.2'!G5,'M.C.5.1'!$B$9) -> 170
D7: Enew | E7: {=SUM(F7:G7*'M.C.5.1'!$B$3:$C$3)} -> 42 | F7: =(F5-F6)*'M.C.5.1'!$D$20 -> 73.818182 | G7: =(G5-G6)*'M.C.5.1'!$D$20 -> 10.181818
D8: Subsidy | E8: {=SUM(F8:G8*'M.C.5.1'!$B$3:$C$3)} -> 12 | F8: =$B$3 -> 12 | G8: =$B$3 -> 12
D9: Eold | E9: {=SUM(F9:G9*'M.C.5.1'!$B$3:$C$3)} -> 69 | F9: =MAX(F5-F6-F7+F8,0) -> 112.18182 | G9: =MAX(G5-G6-G7+G8,0) -> 25.818182
A11: TASK B | F11: TASK C
B12: T = 0 | C12: T = 1 | F12: E(DS) | G12: =E9 -> 69
C13: Up-State | D13: Down-state | F13: E(CG) | G13: =B18 -> 66
A14: V(Firm) | B14: {=SUM(C14:D14*'M.C.5.1'!$B$3:$C$3)} -> 269 | C14: ='M.C.5.1'!C14+'M.C.5.1'!$C$7 -> 344 | D14: ='M.C.5.1'!D14+'M.C.5.1'!$C$7 -> 194 | F14: DS is better due to support in every state. CG is implemented only in bad state
A15: Dsenior | B15: {=SUM(C15:D15*'M.C.5.1'!$B$3:$C$3)} -> 170 | C15: =IF(C14-'M.C.5.1'!$B$9<0,'M.C.5.2'!C14,'M.C.5.1'!$B$9) -> 170 | D15: =IF(D14-'M.C.5.1'!$B$9<0,'M.C.5.2'!D14,'M.C.5.1'!$B$9) -> 170
A16: Djunior (firm payoff) | B16: 42 | C16: =IF(C14-C15<'M.C.5.1'!$C$6,'M.C.5.2'!C14-'M.C.5.2'!C15,'M.C.5.1'!$C$6) -> 42 | D16: =IF(D14-D15<'M.C.5.1'!$C$6,'M.C.5.2'!D14-'M.C.5.2'!D15,'M.C.5.1'!$C$6) -> 24
A17: Djunior (credit guarantee) | B17: {=SUM(C17:D17*'M.C.5.1'!$B$3:$C$3)} -> 9 | C17: ='M.C.5.1'!$C$6-'M.C.5.2'!C16 -> 0 | D17: ='M.C.5.1'!$C$6-'M.C.5.2'!D16 -> 18 | F17: Fiscal cost (DS) | G17: =E8 -> 12
A18: E | B18: =B14-B15-B16+B17 -> 66 | C18: =C14-C15-C16 -> 132 | D18: =D14-D15-D16 -> 0 | F18: Fiscal cost (CG) | G18: =B17 -> 9

Sheet M.C.5.3
A1: Mini-case 5.3
A2: Firm value 1 | B2: Manager | C2: Investors | F2: TASK A | J2: TASK B
A3: Probabilities | B3: 1 | C3: 0.5 | D3: 0.5 | F3: V0,investors,w/o proj.(Firm) | G3: V0,investors(Firm) | H3: Share of V0,investors(Firm) | J3: Perspective | K3: Manager | L3: Investors
A4: V0(Firm) | B4: 290 | C4: ='M.C.5.1'!B4 -> 290 | D4: ='M.C.5.1'!C4 -> 140 | F4: {=SUM(C4:D4*C3:D3)} -> 215 | G4: =F4+'M.C.5.1'!C7 -> 269 | H4: ='M.C.5.1'!C6/'M.C.5.3'!G4 -> 0.15613383 | J4: Date | K4: T = 0 | L4: T = 0 | M4: T = 1
M5: Up-state | N5: Down-state
A6: Firm value 2 | B6: Manager | C6: Investors | F6: Date | G6: T = 0 | J6: V(Firm) | K6: =B4+'M.C.5.1'!C7 -> 344 | L6: {=SUM(M6:N6*C3:D3)} -> 269 | M6: =C4+'M.C.5.1'!$C$7 -> 344 | N6: =D4+'M.C.5.1'!$C$7 -> 194
A7: Probabilities | B7: 1 | C7: 0.5 | D7: 0.5 | F7: Perspective | G7: Manager | H7: Investors | J7: D | K7: ='M.C.5.1'!C6 -> 42 | L7: {=SUM(M7:N7*C3:D3)} -> 42 | M7: ='M.C.5.1'!$C$6 -> 42 | N7: ='M.C.5.1'!$C$6 -> 42
A8: V0(Firm) | B8: 140 | C8: 290 | D8: 140 | F8: V0,manager(Firm) | G8: =B4+'M.C.5.1'!C7 -> 344 | H8: =G4 -> 269 | J8: E | K8: =K6-K7 -> 302 | L8: =L6-L7 -> 227 | M8: =M6-M7 -> 302 | N8: =N6-N7 -> 152
F9: Enew | G9: =G8*$H$4 -> 53.710037 | H9: =H8*$H$4 -> 42
A10: TASK C | F10: Eold | G10: =G8-G9 -> 290.28996 | H10: =H8-H9 -> 227
A11: The manager will finance the project with debt. Basically, it is value of equity for old share holders what she maximizes and we need to compare the real equity of value in both scenarios to the case without the project. Although in case of equity-financing Eold increases too (slightly), the debt financing doesn't expose the company to the investors' payoff which in reality is greater than investors think. Thus, considering information in manager's possession, debt is cheaper and E is going to be maximized
F12: TASK D | J12: TASK E
F13: V0,investors,w/o proj.(Firm) | G13: V0,investors(Firm) | H13: Share of V0,investors(Firm) | J13: Perspective | K13: Manager | L13: Investors
F14: {=SUM(C8:D8*C7:D7)} -> 215 | G14: =F14+'M.C.5.1'!C7 -> 269 | H14: ='M.C.5.1'!C6/'M.C.5.3'!G14 -> 0.15613383 | J14: Date | K14: T = 0 | L14: T = 0 | M14: T = 1
M15: Up-state | N15: Down-state
F16: Date | G16: T = 0 | J16: V(Firm) | K16: =B8+'M.C.5.1'!C7 -> 194 | L16: {=SUM(M16:N16*C3:D3)} -> 269 | M16: =C8+'M.C.5.1'!C7 -> 344 | N16: =D8+'M.C.5.1'!C7 -> 194
F17: Perspective | G17: Manager | H17: Investors | J17: D | K17: =L17 -> 42 | L17: {=SUM(M17:N17*C7:D7)} -> 42 | M17: ='M.C.5.1'!$C$6 -> 42 | N17: ='M.C.5.1'!$C$6 -> 42
F18: V0,manager(Firm) | G18: =B8+'M.C.5.1'!C7 -> 194 | H18: =G14 -> 269 | J18: E | K18: =K16-K17 -> 152 | L18: =L16-L17 -> 227 | M18: =M16-M17 -> 302 | N18: =N16-N17 -> 152
F19: Enew | G19: =G18*$H$14 -> 30.289963 | H19: =H18*$H$14 -> 42
F20: Eold | G20: =G18-G19 -> 163.71004 | H20: =H18-H19 -> 227
A22: TASK F, G | B22: She will raise equity as the old shareholders value in company will be greater in this case. Basically, the signal of equity-financing in this case indicates low firm value. It's quite easy to observe in example from the manager's perspective: the lower is the value of the firm, the lower payoff new equity holder will gain in reality. The firm is simply not ready for the fixed debt payment as it will reduce equity value more significantly
I59: Share of V0,manager,post-investment

Sheet M.C.5.4
A1: Mini-case 5.4
A2: Assumptions | F2: Profit | G2: T = 1 (no RM activities) | I2: T = 1 (RM) | J2: T = 2 | K2: T = 12
A3: rf | B3: TC | C3: NOL carryforward offset rate cap | D3: RM cost | F3: Probabilities | G3: 0.5 | H3: 0.5 | I3: 1 | J3: 1 | K3: 1
A4: 0 | B4: 0.3 | C4: 0.5 | D4: 0 | F4: π | G4: 500 | H4: -400 | I4: {=SUM(G4:H4*G3:H3)} -> 50 | J4: 300 | K4: 500
A6: TASK A | G6: TASK B
A7: Without RM | B7: T = 1 (firm profits) | C7: T = 1 (firm faces losses) | D7: T = 2 (firm profits) | E7: T = 2 (firm faces losses) | G7: With RM | H7: T = 1 | I7: T = 2
A8: Probabilities | B8: 0.5 | C8: 0.5 | D8: 0.5 | E8: 0.5 | G8: Probabilities | H8: 1 | I8: 1
A9: NOL tax shield | B9: 0 | C9: 0 | D9: 0 | E9: =IF(J4-ABS(H4)>(1-C4)*J4,ABS(H4),(1-C4)*J4) -> 150 | G9: NOL tax shield | H9: 0 | I9: 0
A10: E[Tax payment] | B10: =G4*B4 -> 150 | C10: 0 | D10: =J4*B4 -> 90 | E10: =(J4-E9)*B4 -> 45 | G10: E[Tax payment] | H10: =I4*B4 -> 15 | I10: =J4*B4 -> 90
A11: After-tax profit | B11: =G4-B10 -> 350 | C11: =H4-C10 -> -400 | D11: =J4-D10 -> 210 | E11: =J4-E10 -> 255 | G11: After-tax profit | H11: =I4-H10 -> 35 | I11: =J4-I10 -> 210
A13: TASK C | D13: TASK D
A14: ERM[V(Firm)] | B14: {=SUM(H11:I11*H8:I8)} -> 245 | D14: Shareholders cannot affect operating risk in this way. To do effective RM actions for the firm profits, one has to impact its idiosyncratic risk so that the companies operating activities generate more stable revenue. It's final operating profit what tax authorities deduct taxs from
A15: Eno RM[V(Firm)] | B15: {=SUM(B11:E11*B8:E8)} -> 207.5
A16: The tax system has fixed corporate taxt rate which means higher taxes for higher profits. Tax bills are set based on the final operating profits, not ist expectation of it. The less risky the revenues are, the lower tax payment is considered for the future profits.
A25: TASK Ei | G25: TASK Eii
A26: Without RM | B26: T = 1 (firm profits) | C26: T = 1 (firm faces losses) | D26: T = 12 (firm profits) | E26: T = 12 (firm faces losses) | G26: With RM | H26: T = 1 | I26: T = 12
A27: Probabilities | B27: 0.5 | C27: 0.5 | D27: 0.5 | E27: 0.5 | G27: Probabilities | H27: 1 | I27: 1
A28: NOL tax shield | B28: 0 | C28: 0 | D28: 0 | E28: 0 | G28: NOL tax shield | H28: 0 | I28: 0
A29: E[Tax payment] | B29: 150 | C29: 0 | D29: =K4*B$4 -> 150 | E29: =K4*$B$4 -> 150 | G29: E[Tax payment] | H29: 15 | I29: 150
A30: After-tax profit | B30: 350 | C30: -400 | D30: =$K$4-$D$29 -> 350 | E30: =$K$4-$D$29 -> 350 | G30: After-tax profit | H30: 35 | I30: 350

Sheet M.C.5.5
A1: Mini-case 5.5
A2: Assumptions | H2: TASK A
A3: rf | B3: ZCDB | C3: ZCDC | D3: FCF1 | E3: Investment cost | F3: CFproj | H3: NPVproj
A4: 0 | B4: 2400 | C4: 2200 | D4: 2050 | E4: 300 | F4: 520 | H4: =F4-E4 -> 220
A6: TASK B | E6: TASK Ci | I6: TASK Di | M6: TASK Dii
A7: Without project | B7: T = 0 | C7: T = 1 | E7: Without project | F7: T = 0 | G7: T = 1 | J7: Not reduced | K7: Reduced | N7: Not reduced | O7: Reduced
A8: FCF | B8: =C8/(1+A4) -> 2050 | C8: =D4 -> 2050 | E8: FCF | F8: 2050 | G8: 2050 | I8: ZCD | J8: 2400 | K8: =C4 -> 2200 | M8: ZCD | N8: 2400 | O8: 2200
A9: D | B9: =IF(B8<$B$4,B8,$B$4) -> 2050 | C9: =IF(C8<$B$4,C8,$B$4) -> 2050 | E9: D | F9: =IF($D$4-$C$4<0,$D$4,$C$4) -> 2050 | G9: =IF($D$4-$C$4<0,$D$4,$C$4) -> 2050 | I9: Contingent | J9: 1200 | K9: 1200 | M9: Contingent | N9: 1200 | O9: 1200
A10: E | B10: =B8-B9 -> 0 | C10: =C8-C9 -> 0 | E10: E | F10: 0 | G10: 0 | I10: Value per debt-holder | J10: =J8/J9 -> 2 | K10: =K8/K9 -> 1.8333333 | M10: Value per debt-holder | N10: 2 | O10: 1.8333333
A12: With project | B12: T = 0 | C12: T = 1 | E12: With project | F12: T = 0 | G12: T = 1 | I12: Bond-holders' decision | J12: Reduce | K12: Not reduce | M12: Bond-holders' decision | N12: Reduce | O12: Not reduce
A13: FCF | B13: 2050 | C13: =D4 -> 2050 | E13: FCF | F13: =$D$4 -> 2050 | G13: =$D$4 -> 2050 | I13: Contingent | J13: 1199 | K13: 1 | M13: Contingent | N13: 1 | O13: 1199
A14: CFproj | B14: 520 | C14: =F4 -> 520 | E14: CFproj | F14: =$F$4 -> 520 | G14: =$F$4 -> 520 | I14: F | J14: =K10 -> 1.8333333 | K14: =J10 -> 2 | M14: F | N14: =O10 -> 1.8333333 | O14: =N10 -> 2
A15: ∑V(Firm) | B15: 2570 | C15: =C13+C14 -> 2570 | E15: ∑V(Firm) | F15: =F13+F14 -> 2570 | G15: =G13+G14 -> 2570 | I15: Total debt | J15: =J13*J14 -> 2198.1667 | K15: =K13*K14 -> 2 | M15: Total debt | N15: =N14*N13 -> 1.8333333 | O15: =O14*O13 -> 2398
A16: D | B16: 2400 | C16: =IF(C15-B4<0,C15,B4) -> 2400 | E16: D | F16: =$C$4 -> 2200 | G16: =$C$4 -> 2200
A17: E | B17: 170 | C17: =C15-C16 -> 170 | E17: E | F17: =F15-F16 -> 370 | G17: =G15-G16 -> 370
B19: With project | C19: Without project | F19: With project | G19: Without project | J19: With project | K19: Without project | N19: With project | O19: Without project
A20: E | B20: =B17 -> 170 | C20: =B10 -> 0 | E20: E | F20: =F17 -> 370 | G20: =F10 -> 0 | I20: E | J20: =F15-(J15+K15) -> 369.83333 | K20: =F10 -> 0 | M20: E | N20: =F15-(O15+N15) -> 170.16667 | O20: =J10 -> 2
A21: Additional investment | B21: =-E4 -> -300 | C21: - | E21: Additional investment | F21: =-E4 -> -300 | G21: - | I21: Additional investment | J21: =-E4 -> -300 | K21: - | M21: Additional investment | N21: =-E4 -> -300 | O21: -
A22: Total | B22: =B20+B21 -> -130 | C22: 0 | E22: Total | F22: =SUM(F20:F21) -> 70 | G22: =G20 -> 0 | I22: Total | J22: =SUM(J20:J21) -> 69.833333 | K22: 0 | M22: Total | N22: =SUM(N20:N21) -> -129.83333 | O22: 0
A23: No, they won't invest due to losses (NPV to E is negative) | E23: Yes, E now invests in the project, as NPV to E is positive
I24: No, she doesn't want to do this. She sees that E will anyway have enough motivation to invest into the project | M24: This example displays the holdout problem. Without additional coordination among debt holders, the debt reduction won't make a difference
A25: TASK Cii | B25: Yes, it's optimal for them: it's actually comparison between getting 2050 (E doesn't realise the project, and 2200 (E realises it under reduced Face value)

Sheet M.C.5.6
A1: Mini-case 5.6
A2: Assumptions
A3: Shares outstanding | B3: MV(Firm) | C3: Equity loss given diversion of funds | D3: Monitoring | F3: Manager's decision | G3: To diverge funds | H3: Not to diverge funds
A4: 2000000 | B4: 40000000 | C4: -3000000 | D4: -300000 | F4: Probability | G4: 0.5 | H4: 0.5
F5: E | G5: =B4 -> 40000000 | H5: =B4+C4 -> 37000000
A6: TASK A
A7: E[Equity value] | B7: {=SUM(G5:H5*G4:H4)} -> 38500000 | E7: TASK B
A8: E[Loss due to diversion] | B8: =B7-B4 -> -1500000 | E8: Quantity of stocks per shareholder | H8: 1
A9: Is it optimal to monitor? | B9: =IF(B8<D4,"YES","NO") -> YES | E9: Shareholders contigent | H9: =A4/H8 -> 2000000
E10: Losses faced by 1 shareholder | H10: =B8/H9 -> -0.75
A11: TASK C | E11: Is it optimal to monitor? | H11: =IF(H10<D4,"YES","NO") -> NO
A12: Price per share | B12: =B4/A4 -> 20
A13: X | B13: =-D4/B12 -> 15000
A15: TASK D | B15: This mini-case displays an example of free-rider problem in terms of monitoring. The company loses its value due to funds diversion only if everyone acts in their own interest and considers only own position when meeting decision whether to invest in monitoring.
